gstreasy/__init__.py
gstreasy/pipeline.py
gstreasy/utils.py
gstreasy/wrapped_caps.py
gstreasy-0.3.1.dist-info/LICENSE
gstreasy-0.3.1.dist-info/METADATA
gstreasy-0.3.1.dist-info/WHEEL
gstreasy-0.3.1.dist-info/top_level.txt
gstreasy-0.3.1.dist-info/RECORD
