Metadata-Version: 2.1
Name: gstreasy
Version: 0.3.1
Summary: Makes using GStreamer in python easy!
Author-email: Dan Davis <dan@dandavis.dev>
License: Apache-2.0
Project-URL: Homepage, https://github.com/danofsteel32/gstreasy
Classifier: Programming Language :: Python :: 3
Classifier: Development Status :: 3 - Alpha
Classifier: Intended Audience :: Developers
Classifier: License :: OSI Approved :: Apache Software License
Requires-Python: >=3.7
License-File: LICENSE
Requires-Dist: attrs
Requires-Dist: numpy
Requires-Dist: PyGObject
Provides-Extra: dev
Requires-Dist: black ; extra == 'dev'
Requires-Dist: flake8 ; extra == 'dev'
Requires-Dist: flake8-isort ; extra == 'dev'
Requires-Dist: flake8-docstrings ; extra == 'dev'
Requires-Dist: mypy ; extra == 'dev'
Requires-Dist: pytest ; extra == 'dev'
Requires-Dist: tox ; extra == 'dev'
Requires-Dist: build ; extra == 'dev'
Provides-Extra: doc
Requires-Dist: pdoc ; extra == 'doc'
